odoo/addons/partner_repair_button/README.rst
odoo/addons/partner_repair_button/__init__.py
odoo/addons/partner_repair_button/__manifest__.py
odoo/addons/partner_repair_button/i18n/it.po
odoo/addons/partner_repair_button/i18n/partner_repair_button.pot
odoo/addons/partner_repair_button/models/__init__.py
odoo/addons/partner_repair_button/models/res_partner.py
odoo/addons/partner_repair_button/readme/CONTRIBUTORS.md
odoo/addons/partner_repair_button/readme/DESCRIPTION.md
odoo/addons/partner_repair_button/readme/USAGE.md
odoo/addons/partner_repair_button/static/description/icon.png
odoo/addons/partner_repair_button/static/description/index.html
odoo/addons/partner_repair_button/tests/__init__.py
odoo/addons/partner_repair_button/tests/tesa_partner_repair_button.py
odoo/addons/partner_repair_button/views/res_partner_views.xml
odoo_addon_partner_repair_button-18.0.1.0.0.4.dist-info/METADATA
odoo_addon_partner_repair_button-18.0.1.0.0.4.dist-info/WHEEL
odoo_addon_partner_repair_button-18.0.1.0.0.4.dist-info/top_level.txt
odoo_addon_partner_repair_button-18.0.1.0.0.4.dist-info/RECORD
